README.md
setup.py
somerandomwrapper/__init__.py
somerandomwrapper/wrapper.py
somerandomwrapper.egg-info/PKG-INFO
somerandomwrapper.egg-info/SOURCES.txt
somerandomwrapper.egg-info/dependency_links.txt
somerandomwrapper.egg-info/requires.txt
somerandomwrapper.egg-info/top_level.txt