Metadata-Version: 2.1
Name: somerandomwrapper
Version: 0.1.0
Summary: A small local Wrapper for Some Random API written on Python.
Home-page: https://github.com/Kerdokan/SomeRandomWrapper
Author-email: support@kerdokan.co
License: UNKNOWN
Platform: UNKNOWN
Classifier: Programming Language :: Python :: 3
Classifier: Operating System :: OS Independent
